Metadata-Version: 2.1
Name: grun-js
Version: 0.0.3
Summary: 调用 node 执行 js，可指定编码
Home-page: https://github.com/Leviathangk/runjs
Author: 郭一会儿
Author-email: 1015295213@qq.com
License: MIT Licence
Keywords: js,grun_js,pyexecjs
Platform: any
